README.md
setup.py
classify/__init__.py
classify/classify.py
classify/client_test.py
classify/network.py
classify/train.py
classify_ifchange.egg-info/PKG-INFO
classify_ifchange.egg-info/SOURCES.txt
classify_ifchange.egg-info/dependency_links.txt
classify_ifchange.egg-info/not-zip-safe
classify_ifchange.egg-info/requires.txt
classify_ifchange.egg-info/top_level.txt