Metadata-Version: 2.1
Name: classify-ifchange
Version: 0.0.5
Summary: nlu service tools for classification
Home-page: https://www.ifchange.com
Author: ai3
Author-email: ai3@ifchange.com
License: Apache License 2.0
Platform: UNKNOWN
